{
    "title": "WOP月刊 - 2023年12月刊",
    "id": 16585962,
    "description": "",
    "last": 1703902431,
    "lastUser": 8843079,
    "started": 1703896746,
    "startedUser": null,
    "postsNum": 6,
    "sticky": false,
    "isLocked": false,
    "version": 1,
    "posts": [
        {
            "id": 6319591,
            "title": "作者贴",
            "poster": 8196010,
            "stamp": 1703896963,
            "revisions": [],
            "children": []
        },
        {
            "id": 6319713,
            "title": "",
            "poster": 8516280,
            "stamp": 1703899586,
            "revisions": [],
            "children": [
                {
                    "id": 6319786,
                    "title": "PLEASE TRY AGAIN 已送达 期待您的五星好评！",
                    "poster": 8196010,
                    "stamp": 1703901123,
                    "revisions": [],
                    "children": []
                },
                {
                    "id": 6319850,
                    "title": "",
                    "poster": 8843079,
                    "stamp": 1703902431,
                    "revisions": [],
                    "children": []
                }
            ]
        },
        {
            "id": 6319839,
            "title": "在Wikidot薯条的广告加了一句",
            "poster": 8843079,
            "stamp": 1703902284,
            "revisions": [],
            "children": [
                {
                    "id": 6319849,
                    "title": "Re: 在Wikidot薯条的广告加了一句",
                    "poster": 8196010,
                    "stamp": 1703902401,
                    "revisions": [],
                    "children": []
                }
            ]
        }
    ]
}