{
    "name": "lun",
    "version": 18,
    "revisions": [
        {
            "revision": 2,
            "global_revision": 1543278019,
            "author": 9331062,
            "stamp": 1775903835,
            "flags": "A",
            "commentary": "已新增标签：故事。 移除标签：批判。"
        },
        {
            "revision": 1,
            "global_revision": 1543155869,
            "author": 9526934,
            "stamp": 1775493475,
            "flags": "A",
            "commentary": "已新增标签：原创, 批判。"
        },
        {
            "revision": 0,
            "global_revision": 1543155865,
            "author": 9526934,
            "stamp": 1775493458,
            "flags": "N",
            "commentary": ""
        }
    ],
    "files": [],
    "page_id": 1468427147,
    "rating": 4,
    "forum_thread": 17707580,
    "tags": [
        "原创",
        "故事"
    ],
    "title": "试评《无限流小说和规则类怪谈小说类型特点的异同》",
    "sitemap_update": 1775903835000,
    "votings": [
        [
            10280217,
            true
        ],
        [
            8708015,
            true
        ],
        [
            8516280,
            true
        ],
        [
            9892553,
            true
        ]
    ],
    "is_locked": false
}