{
    "name": "xiegezi",
    "version": 18,
    "revisions": [
        {
            "revision": 64,
            "global_revision": 1532862883,
            "author": 8516280,
            "stamp": 1759987309,
            "flags": "S",
            "commentary": ""
        },
        {
            "revision": 63,
            "global_revision": 1532862870,
            "author": 8516280,
            "stamp": 1759987219,
            "flags": "S",
            "commentary": ""
        },
        {
            "revision": 62,
            "global_revision": 1531818235,
            "author": 8516280,
            "stamp": 1756380247,
            "flags": "S",
            "commentary": ""
        },
        {
            "revision": 61,
            "global_revision": 1531809532,
            "author": 8516280,
            "stamp": 1756346678,
            "flags": "S",
            "commentary": ""
        },
        {
            "revision": 60,
            "global_revision": 1531809385,
            "author": 8516280,
            "stamp": 1756346126,
            "flags": "S",
            "commentary": ""
        },
        {
            "revision": 59,
            "global_revision": 1531259271,
            "author": 8516280,
            "stamp": 1753773468,
            "flags": "S",
            "commentary": ""
        },
        {
            "revision": 58,
            "global_revision": 1531177567,
            "author": 8516280,
            "stamp": 1753437494,
            "flags": "S",
            "commentary": ""
        },
        {
            "revision": 57,
            "global_revision": 1531177555,
            "author": 8516280,
            "stamp": 1753437427,
            "flags": "S",
            "commentary": ""
        },
        {
            "revision": 56,
            "global_revision": 1531177544,
            "author": 8516280,
            "stamp": 1753437382,
            "flags": "S",
            "commentary": ""
        },
        {
            "revision": 55,
            "global_revision": 1531177485,
            "author": 8516280,
            "stamp": 1753437020,
            "flags": "S",
            "commentary": ""
        },
        {
            "revision": 54,
            "global_revision": 1531177354,
            "author": 8516280,
            "stamp": 1753436469,
            "flags": "S",
            "commentary": ""
        },
        {
            "revision": 53,
            "global_revision": 1531177301,
            "author": 8516280,
            "stamp": 1753436322,
            "flags": "S",
            "commentary": ""
        },
        {
            "revision": 52,
            "global_revision": 1531177258,
            "author": 8516280,
            "stamp": 1753436030,
            "flags": "S",
            "commentary": ""
        },
        {
            "revision": 51,
            "global_revision": 1523291288,
            "author": 8516280,
            "stamp": 1722343401,
            "flags": "S",
            "commentary": ""
        },
        {
            "revision": 50,
            "global_revision": 1523262290,
            "author": 8516280,
            "stamp": 1722173959,
            "flags": "S",
            "commentary": ""
        },
        {
            "revision": 49,
            "global_revision": 1523262253,
            "author": 8516280,
            "stamp": 1722173760,
            "flags": "S",
            "commentary": ""
        },
        {
            "revision": 48,
            "global_revision": 1523262241,
            "author": 8516280,
            "stamp": 1722173676,
            "flags": "S",
            "commentary": ""
        },
        {
            "revision": 47,
            "global_revision": 1523262238,
            "author": 8516280,
            "stamp": 1722173643,
            "flags": "S",
            "commentary": ""
        },
        {
            "revision": 46,
            "global_revision": 1523262219,
            "author": 8516280,
            "stamp": 1722173549,
            "flags": "S",
            "commentary": ""
        },
        {
            "revision": 45,
            "global_revision": 1523262129,
            "author": 8516280,
            "stamp": 1722173116,
            "flags": "S",
            "commentary": ""
        },
        {
            "revision": 44,
            "global_revision": 1523262118,
            "author": 8516280,
            "stamp": 1722172984,
            "flags": "S",
            "commentary": ""
        },
        {
            "revision": 43,
            "global_revision": 1523194593,
            "author": 8516280,
            "stamp": 1721812979,
            "flags": "S",
            "commentary": ""
        },
        {
            "revision": 42,
            "global_revision": 1523150182,
            "author": 8516280,
            "stamp": 1721568096,
            "flags": "S",
            "commentary": ""
        },
        {
            "revision": 41,
            "global_revision": 1523150129,
            "author": 8516280,
            "stamp": 1721567753,
            "flags": "S",
            "commentary": ""
        },
        {
            "revision": 40,
            "global_revision": 1523148800,
            "author": 8516280,
            "stamp": 1721560233,
            "flags": "S",
            "commentary": ""
        },
        {
            "revision": 39,
            "global_revision": 1523148712,
            "author": 8516280,
            "stamp": 1721559535,
            "flags": "S",
            "commentary": ""
        },
        {
            "revision": 38,
            "global_revision": 1523148611,
            "author": 8516280,
            "stamp": 1721558864,
            "flags": "S",
            "commentary": ""
        },
        {
            "revision": 37,
            "global_revision": 1523148607,
            "author": 8516280,
            "stamp": 1721558826,
            "flags": "S",
            "commentary": ""
        },
        {
            "revision": 36,
            "global_revision": 1523148514,
            "author": 8516280,
            "stamp": 1721558323,
            "flags": "S",
            "commentary": ""
        },
        {
            "revision": 35,
            "global_revision": 1523148380,
            "author": 8516280,
            "stamp": 1721557432,
            "flags": "S",
            "commentary": ""
        },
        {
            "revision": 34,
            "global_revision": 1523148366,
            "author": 8516280,
            "stamp": 1721557317,
            "flags": "S",
            "commentary": ""
        },
        {
            "revision": 33,
            "global_revision": 1523148337,
            "author": 8516280,
            "stamp": 1721557155,
            "flags": "S",
            "commentary": ""
        },
        {
            "revision": 32,
            "global_revision": 1523145040,
            "author": 8516280,
            "stamp": 1721542273,
            "flags": "S",
            "commentary": ""
        },
        {
            "revision": 31,
            "global_revision": 1523145026,
            "author": 8516280,
            "stamp": 1721542193,
            "flags": "S",
            "commentary": ""
        },
        {
            "revision": 30,
            "global_revision": 1523145021,
            "author": 8516280,
            "stamp": 1721542160,
            "flags": "S",
            "commentary": ""
        },
        {
            "revision": 29,
            "global_revision": 1523144971,
            "author": 8516280,
            "stamp": 1721542004,
            "flags": "S",
            "commentary": ""
        },
        {
            "revision": 28,
            "global_revision": 1523144882,
            "author": 8516280,
            "stamp": 1721541592,
            "flags": "S",
            "commentary": ""
        },
        {
            "revision": 27,
            "global_revision": 1523144872,
            "author": 8516280,
            "stamp": 1721541519,
            "flags": "S",
            "commentary": ""
        },
        {
            "revision": 26,
            "global_revision": 1523144842,
            "author": 8516280,
            "stamp": 1721541360,
            "flags": "S",
            "commentary": ""
        },
        {
            "revision": 25,
            "global_revision": 1523144776,
            "author": 8516280,
            "stamp": 1721541033,
            "flags": "S",
            "commentary": ""
        },
        {
            "revision": 24,
            "global_revision": 1523144771,
            "author": 8516280,
            "stamp": 1721540976,
            "flags": "S",
            "commentary": ""
        },
        {
            "revision": 23,
            "global_revision": 1523091896,
            "author": 8516280,
            "stamp": 1721301041,
            "flags": "S",
            "commentary": ""
        },
        {
            "revision": 22,
            "global_revision": 1523091856,
            "author": 8516280,
            "stamp": 1721300966,
            "flags": "S",
            "commentary": ""
        },
        {
            "revision": 21,
            "global_revision": 1523091848,
            "author": 8516280,
            "stamp": 1721300917,
            "flags": "S",
            "commentary": ""
        },
        {
            "revision": 20,
            "global_revision": 1523042204,
            "author": 8516280,
            "stamp": 1721008648,
            "flags": "S",
            "commentary": ""
        },
        {
            "revision": 19,
            "global_revision": 1523042197,
            "author": 8516280,
            "stamp": 1721008607,
            "flags": "S",
            "commentary": ""
        },
        {
            "revision": 18,
            "global_revision": 1523042182,
            "author": 8516280,
            "stamp": 1721008503,
            "flags": "S",
            "commentary": ""
        },
        {
            "revision": 17,
            "global_revision": 1523042172,
            "author": 8516280,
            "stamp": 1721008428,
            "flags": "S",
            "commentary": ""
        },
        {
            "revision": 16,
            "global_revision": 1521297530,
            "author": 8516280,
            "stamp": 1719379481,
            "flags": "S",
            "commentary": ""
        },
        {
            "revision": 15,
            "global_revision": 1521297377,
            "author": 8516280,
            "stamp": 1719378349,
            "flags": "S",
            "commentary": ""
        },
        {
            "revision": 14,
            "global_revision": 1521028640,
            "author": 8516280,
            "stamp": 1718955114,
            "flags": "S",
            "commentary": ""
        },
        {
            "revision": 13,
            "global_revision": 1521016673,
            "author": 8516280,
            "stamp": 1718873189,
            "flags": "S",
            "commentary": ""
        },
        {
            "revision": 12,
            "global_revision": 1520587131,
            "author": 8516280,
            "stamp": 1717304970,
            "flags": "S",
            "commentary": ""
        },
        {
            "revision": 11,
            "global_revision": 1517900220,
            "author": 8516280,
            "stamp": 1706599804,
            "flags": "S",
            "commentary": ""
        },
        {
            "revision": 10,
            "global_revision": 1517900215,
            "author": 8516280,
            "stamp": 1706599755,
            "flags": "S",
            "commentary": ""
        },
        {
            "revision": 9,
            "global_revision": 1517390592,
            "author": 8516280,
            "stamp": 1705118280,
            "flags": "S",
            "commentary": ""
        },
        {
            "revision": 8,
            "global_revision": 1517076507,
            "author": 8516280,
            "stamp": 1703995856,
            "flags": "S",
            "commentary": ""
        },
        {
            "revision": 7,
            "global_revision": 1517002317,
            "author": 8516280,
            "stamp": 1703592285,
            "flags": "S",
            "commentary": ""
        },
        {
            "revision": 6,
            "global_revision": 1516948781,
            "author": 8516280,
            "stamp": 1703307857,
            "flags": "S",
            "commentary": ""
        },
        {
            "revision": 5,
            "global_revision": 1516765494,
            "author": 8516280,
            "stamp": 1702741146,
            "flags": "S",
            "commentary": ""
        },
        {
            "revision": 4,
            "global_revision": 1516765461,
            "author": 8516280,
            "stamp": 1702741042,
            "flags": "S",
            "commentary": ""
        },
        {
            "revision": 3,
            "global_revision": 1516765402,
            "author": 8516280,
            "stamp": 1702740760,
            "flags": "S",
            "commentary": ""
        },
        {
            "revision": 2,
            "global_revision": 1516720852,
            "author": 8516280,
            "stamp": 1702625469,
            "flags": "S",
            "commentary": ""
        },
        {
            "revision": 1,
            "global_revision": 1516716153,
            "author": 8516280,
            "stamp": 1702608091,
            "flags": "A",
            "commentary": "已新增标签：作者。"
        },
        {
            "revision": 0,
            "global_revision": 1516716121,
            "author": 8516280,
            "stamp": 1702608056,
            "flags": "N",
            "commentary": ""
        }
    ],
    "files": [],
    "page_id": 1451809556,
    "rating": 6,
    "forum_thread": 16522687,
    "tags": [
        "作者"
    ],
    "title": "Xiegezi的咖啡馆",
    "sitemap_update": 1759987309000,
    "votings": [
        [
            8457298,
            true
        ],
        [
            8446836,
            true
        ],
        [
            8437582,
            true
        ],
        [
            8516280,
            true
        ],
        [
            8196010,
            true
        ],
        [
            8876086,
            true
        ]
    ],
    "is_locked": false
}